mlx/warnings/__init__.py
mlx/warnings/__main__.py
mlx/warnings/__version__.py
mlx/warnings/code_quality.py
mlx/warnings/exceptions.py
mlx/warnings/junit_checker.py
mlx/warnings/polyspace_checker.py
mlx/warnings/regex_checker.py
mlx/warnings/robot_checker.py
mlx/warnings/warnings.py
mlx/warnings/warnings_checker.py
mlx_warnings-6.1.1.dist-info/licenses/LICENSE
mlx_warnings-6.1.1.dist-info/licenses/NOTICE
mlx_warnings-6.1.1.dist-info/METADATA
mlx_warnings-6.1.1.dist-info/WHEEL
mlx_warnings-6.1.1.dist-info/entry_points.txt
mlx_warnings-6.1.1.dist-info/top_level.txt
mlx_warnings-6.1.1.dist-info/RECORD
