Metadata-Version: 2.4
Name: mlx.warnings
Version: 6.1.1
Summary: Command-line alternative for https://github.com/jenkinsci/warnings-plugin. Useable with plugin-less CI systems.
Author: Jasper Craeghs, Joke Waumans, Stein Heselmans
Author-email: Bavo Van Achte <bavo.van.achte@gmail.com>, Crt Mori <crt@the-mori.com>
License: Apache License, Version 2.0
Project-URL: Documentation, https://melexis.github.io/warnings-plugin
Project-URL: Source, https://github.com/melexis/warnings-plugin
Project-URL: Tracker, https://github.com/melexis/warnings-plugin/issues
Keywords: Gitlab CI,warnings,CI
Classifier: Development Status :: 5 - Production/Stable
Classifier: Intended Audience :: Developers
Classifier: License :: OSI Approved :: Apache Software License
Classifier: Operating System :: Unix
Classifier: Operating System :: POSIX
Classifier: Operating System :: Microsoft :: Windows
Classifier: Programming Language :: Python
Classifier: Programming Language :: Python :: 3
Classifier: Programming Language :: Python :: 3.8
Classifier: Programming Language :: Python :: 3.9
Classifier: Programming Language :: Python :: 3.10
Classifier: Programming Language :: Python :: 3.11
Classifier: Programming Language :: Python :: 3.12
Classifier: Topic :: Utilities
Requires-Python: >=3.8
License-File: LICENSE
License-File: NOTICE
Requires-Dist: junitparser<2.0,>=1.0.0
Requires-Dist: ruamel.yaml>=0.17.21
Dynamic: license-file
